entipy/__init__.py
entipy/datamodels.py
entipy/resolvers.py
entipy-0.0.3.dist-info/METADATA
entipy-0.0.3.dist-info/WHEEL
entipy-0.0.3.dist-info/licenses/LICENSE
entipy-0.0.3.dist-info/RECORD
