Metadata-Version: 2.1
Name: entipy
Version: 0.0.3
Summary: EntiPy is a Python library that implements an incremental clustering approach to entity resolution.
Project-URL: Repository, https://github.com/Alteheit/entipy
Author-email: Joe Ilagan <joe@archmob.com>
License-File: LICENSE
Classifier: Development Status :: 2 - Pre-Alpha
Classifier: Operating System :: OS Independent
Requires-Python: >=3.11
Requires-Dist: sortedcontainers>=2.4.0
